shelf.py
shelf_backup-0.1.1.dist-info/licenses/LICENSE
shelf_backup-0.1.1.dist-info/METADATA
shelf_backup-0.1.1.dist-info/WHEEL
shelf_backup-0.1.1.dist-info/entry_points.txt
shelf_backup-0.1.1.dist-info/top_level.txt
shelf_backup-0.1.1.dist-info/RECORD
