Metadata-Version: 2.4
Name: shelf-backup
Version: 0.1.1
Summary: A stupidly simple backup tool: single file with zero dependencies
Author: Radhe
License: MIT
Project-URL: Homepage, https://github.com/rdyv/shelf
Project-URL: Repository, https://github.com/rdyv/shelf
Project-URL: Issues, https://github.com/rdyv/shelf/issues
Keywords: backup,restore,dotfiles,git,homebrew,simple
Classifier: Development Status :: 5 - Production/Stable
Classifier: Intended Audience :: End Users/Desktop
Classifier: License :: OSI Approved :: MIT License
Classifier: Operating System :: OS Independent
Classifier: Programming Language :: Python :: 3
Classifier: Programming Language :: Python :: 3.8
Classifier: Programming Language :: Python :: 3.9
Classifier: Programming Language :: Python :: 3.10
Classifier: Programming Language :: Python :: 3.11
Classifier: Programming Language :: Python :: 3.12
Classifier: Topic :: System :: Archiving :: Backup
Classifier: Topic :: System :: Systems Administration
Requires-Python: >=3.8
License-File: LICENSE
Provides-Extra: dev
Requires-Dist: black>=23.0.0; extra == "dev"
Requires-Dist: flake8>=6.0.0; extra == "dev"
Dynamic: license-file
